{
  "url": "https://www.presidency.ucsb.edu/documents/executive-order-225",
  "eo_number": "225",
  "title": "Executive Order",
  "date_str": "February 11, 1889",
  "date_iso": "1889-02-11",
  "president": "Grover Cleveland",
  "text": "UNITED STATES CIVIL SERVICE COMMISSION,\nWashington, D.C., February 9, 1889.\nThe PRESIDENT.\nSIR: This Commission has the honor to recommend that the order heretofore approved by you authorizing noncompetitive examination under General Rule III, section 2, clause (e) , to test fitness for certain designated places in the classified departmental service, may be amended by the revocation of so much of the order above referred to as provides for the appointment upon noncompetitive examination of \"inspector of electric lights\" in the office of the Secretary in the Treasury Department.\nVery respectfully,\nCHAS. LYMAN,\nUnited States Civil Service Commissioner\n.\nApproved, February 11, 1889.\nGROVER CLEVELAND"
}