{
  "url": "https://www.presidency.ucsb.edu/documents/executive-order-5237-reserving-certain-described-lands-for-classification-california",
  "eo_number": "5237",
  "title": "Executive Order 5237—Reserving Certain Described Lands for Classification, California",
  "date_str": "December 10, 1929",
  "date_iso": "1929-12-10",
  "president": "Herbert Hoover",
  "text": "Under authority of the act of Congress approved June 25, 1910 (36 Stat. 847), as amended by the Act of August 24, 1912 (37 Stat. 497), and subject to the conditions therein expressed, it is hereby ordered that the unreserved public lands within the following listed townships be, and the same are hereby temporarily withdrawn for classification, subject to prior valid rights:\nHumboldt Meridian\nIn Tps. 7, 11 and 12 N., R. 1 E.;\nIn T. 6 N., R. 1 W.;\nIn Tps. 4 and 5 S., R. 1 E.;\nIn T. 5 S., R. 2 E.;\nIn Tps. 3 and 4 S., R. 1 W.;\nIn Tps. 1, 2 and 3 S., R. 2 W.;\nIn T. IS., R. 3 W.;\nMt. Diablo Meridian\nIn Tps. 19, 20 and 21 N., R. 17 W.;\nIn T. 24 N., Rs. 18 and 19 W.\nThis order shall continue in full force and effect unless and until revoked by the President or by act of Congress.\nHERBERT HOOVER\nThe White House,\nDecember 10, 1929."
}