{
  "url": "https://www.presidency.ucsb.edu/documents/executive-order-5497-power-site-restoration-no-454",
  "eo_number": "5497",
  "title": "Executive Order 5497—Power-Site Restoration No. 454",
  "date_str": "November 24, 1930",
  "date_iso": "1930-11-24",
  "president": "Herbert Hoover",
  "text": "New Mexico\nSo much of the order of September 30, 1916, creating Power-Site Reserve No. 547, as affects the lands hereinafter described is hereby revoked:\nNEW MEXICO MERIDIAN\nT. 17 S., R. 20 E., sec. 7, lots 1 and 2;\nsec. 13, S. ½ NW. ¼, N. ½ SW. ¼;\nsec. 14, S. ½ N. ½, N. ½ S. ½;\nsec. 15, S. ½ N. ½;\nsec. 17, S. ½;\nsec. 18, lots 1, 2, 3, and 4, SE. ¼ NW. ¼, E. ½ SW. ¼;\nsec. 19, lots 1 and 2, S. ½ NE. ¼, E. ½ NW. ¼, NE. ¼ SW. ¼, N. ½ SE. ¼;\nsec. 20, N. ½ NE. ¼, SW. ¼ NW. ¼, N. ½ S. ½;\nsec. 21, S. ½ NE. ¼, SE. ¼ NW. ¼, N. ½ S. ½;\nsec. 22, N. ½;\nsec. 23, N. ½.\nHERBERT HOOVER\nThe White House,\nNovember 24, 1930."
}