{
  "url": "https://www.presidency.ucsb.edu/documents/executive-order-5039-general-joe-wheeler-dam",
  "eo_number": "5039",
  "title": "Executive Order 5039—General Joe Wheeler Dam",
  "date_str": "February 04, 1929",
  "date_iso": "1929-02-04",
  "president": "Calvin Coolidge",
  "text": "It is hereby directed that the Dam proposed in the report to Congress, House Document 1262—64th Congress, First Sesssion, and referred to therein as Dam No. 3, be named General Joe Wheeler Dam.\nCALVIN COOLIDGE\nThe White House,\nFebruary 4, 1929."
}