{
  "url": "https://www.presidency.ucsb.edu/documents/executive-order-7213-enforcement-the-northern-pacific-halibut-act",
  "eo_number": "7213",
  "title": "Executive Order 7213—Enforcement of the Northern Pacific Halibut Act",
  "date_str": "October 24, 1935",
  "date_iso": "1935-10-24",
  "president": "Franklin D. Roosevelt",
  "text": "By virtue of and pursuant to the authority vested in me by section 7 of the Northern Pacific Halibut Act (47 Stat. 142), I hereby designate such vessels of the Coast Guard as the Commandant of the Coast Guard shall assign for that purpose to patrol the territorial waters of the United States, as defined in the said act, for the enforcement of the said act and the Convention for the Preservation of the Halibut Fisheries of the Northern Pacific Ocean and the Bering Sea.\nFRANKLIN D. ROOSEVELT\nThe White House,\nOctober 24, 1935."
}