{
  "url": "https://www.presidency.ucsb.edu/documents/executive-order-8152-establishing-lake-elsie-migratory-waterfowl-refuge",
  "eo_number": "8152",
  "title": "Executive Order 8152—Establishing Lake Elsie Migratory Waterfowl Refuge",
  "date_str": "June 12, 1939",
  "date_iso": "1939-06-12",
  "president": "Franklin D. Roosevelt",
  "text": "NORTH DAKOTA\nBy virtue of and pursuant to the authority vested in me as President of the United States, it is ordered that all lands and waters owned or controlled by the United States within the following-described area, comprising 635 acres, more or less, in Richland County, North Dakota, be, and they are hereby, reserved\nand set apart, subject to valid rights, for the use of the Department of Agriculture as a refuge and breeding ground for migratory birds and other wildlife:\nFIFTH PRINCIPAL MERIDIAN\nT. 130 N., R. 50 W.,\nsec. 26, that part of lot 3 lying west of a line running North from the meander point common to lots 3 and 4;\nsec. 27, lots 1 to 4, inclusive, and E½W½;\nsec. 34, NW¼NE¼;\nand lands and lands under water within the meander line of the lake in secs. 22, 23, 26, 27, 34, and 35.\nIt is unlawful for any person to pursue, hunt, trap, capture, willfully disturb, or kill any bird or wild animal of any kind whatsoever within the limits of the refuge, or to enter thereon, except under such rules and regulations as may be prescribed by the Secretary of Agriculture.\nThis reservation shall be known as the Lake Elsie Migratory Waterfowl Refuge.\nFRANKLIN D ROOSEVELT\nThe White House,\nJune 12, 1939."
}