{
  "url": "https://www.presidency.ucsb.edu/documents/executive-order-8432-revocation-executive-order-no-5208-october-12-1929-withdrawing-public",
  "eo_number": "8432",
  "title": "Executive Order 8432—Revocation of Executive Order No. 5208 of October 12, 1929, Withdrawing Public Lands",
  "date_str": "June 08, 1940",
  "date_iso": "1940-06-08",
  "president": "Franklin D. Roosevelt",
  "text": "NEVADA\nBy virtue of the authority vested in me by the act of June 25, 1910, c. 421, 36 Stat. 847, Executive Order No. 5208 of October 12, 1929, withdrawing public lands in Nevada pending a resurvey, and heretofore partially revoked, is hereby revoked as to the remainder of the lands affected thereby.\nThis order shall become effective upon the date, of the official filing of the plat of the resurvey of the lands involved.\nFRANKLIN D. ROOSEVELT\nThe White House,\nJune 8, 1940."
}