{
  "url": "https://www.presidency.ucsb.edu/documents/executive-order-8656-exemption-ovilup-h-george-from-compulsory-retirement-for-age",
  "eo_number": "8656",
  "title": "Executive Order 8656—Exemption of Ovilup H. George From Compulsory Retirement for Age",
  "date_str": "February 03, 1941",
  "date_iso": "1941-02-03",
  "president": "Franklin D. Roosevelt",
  "text": "Whereas\n, in my judgment, the public interest requires that Ovilup H. George, chief pipefitter and fire chief, Government Printing Office, who, during the current month, will reach the retirement age prescribed for automatic separation from the service, applicable to him, be exempted from compulsory retirement for age for a period of one year:\nNow, Therefore\n, by virtue of and pursuant to the authority vested in me by section 204 of the act of June 30, 1932, 47 Stat. 382, 404 (U.S.C., title 5, sec. 715a), I hereby exempt the said Ovilup H. George from compulsory retirement for age for a period of one year ending February 28, 1942.\nFRANKLIN D ROOSEVELT\nThe White House,\nFebruary 3, 1941."
}