{
  "url": "https://www.presidency.ucsb.edu/documents/executive-order-5360-power-site-restoration-no-438",
  "eo_number": "5360",
  "title": "Executive Order 5360—Power-Site Restoration No. 438",
  "date_str": "June 03, 1930",
  "date_iso": "1930-06-03",
  "president": "Herbert Hoover",
  "text": "Oregon, California, and Idaho\nWILLAMETTE MERIDIAN, OREGON\nWILLAMETTE RIVER TRIBUTARIES, OREGON\nSo much of the order of December 12, 1917, creating Power-Site Reserve No. 661, as affects the lands hereinafter described, is hereby revoked:\nT. 4 S., R. 4 W., sec. 13, lot 1.\nT. 7 S., R. 6 W., sec. 33, SE. ¼.\nT. 8 S., R. 6 W., sec. 5, S. ½ of N. ½.\nT. 8 S., R. 7 W., sec. 1, SW. ¼, NW. ¼ of SE. ¼.\nWILLAMETTE RIVER BASIN, OREGON\nSo much of the order of December 12, 1917, creating Power-Site Reserve No. 664, as affects the lands hereinafter described, is hereby revoked:\nT. 1 S., R. 4 W., sec. 33, lots 1 and 8;\nsec. 35, lot 3.\nMOUNT DIABLO MERIDIAN, CALIFORNIA\nSTANISLAUS RIVER, CALIFORNIA\nSo much of the order of December 20, 1909, creating Power-Site Reserve No. 86, as affects the lands hereinafter described, is hereby revoked:\nT. 2 N., R. 14 E., sec. 20, S. ½ of NE. ¼ of NW. ¼, SE. ¼ of NW. ¼ of NW. ¼, N. ½ of S. ½ of NW. ¼.\nKLAMATH RIVER, CALIFORNIA\nSo much of the order of October 28, 1912, creating Power-Site Reserve No. 302, as affects the lands hereinafter described, is hereby revoked:\nT. 48 N., R. 4 W., sec. 30, SW. ¼ of SW. ¼.\nBOISE MERIDIAN, IDAHO\nSALMON RIVER NO. 4, IDAHO\nSo much of the order of October 22, 1912, creating Power-Site Reserve No. 305, as affects the lands hereinafter described, is hereby revoked:\nT. 27 N. R. 1 E., sec. 34, N. ½ of SW. ¼.\nHERBERT HOOVER\nThe White House,\nJune 3, 1930."
}