{
  "url": "https://www.presidency.ucsb.edu/documents/executive-order-6236-appointment-henry-roe-cloud",
  "eo_number": "6236",
  "title": "Executive Order 6236—Appointment of Henry Roe Cloud",
  "date_str": "July 28, 1933",
  "date_iso": "1933-07-28",
  "president": "Franklin D. Roosevelt",
  "text": "Henry Roe Cloud may be appointed without competitive civil-service examination Superintendent of the Haskell Institute, Lawrence, Kansas. This institution is an important nonreservation Indian school. Mr. Cloud is a Winnebago Indian. He has had long and varied experience in Indian education; he has been a field representative in the Indian Service; and he is eminently fitted for the superintendency.\nThis order is issued upon the recommendation of the Secretary of the Interior.\nFRANKLIN D. ROOSEVELT\nThe White House,\nJuly 28, 1933."
}