{
  "url": "https://www.presidency.ucsb.edu/documents/executive-order-6070-authorizing-the-appointment-mrs-mary-mcclung",
  "eo_number": "6070",
  "title": "Executive Order 6070—Authorizing the Appointment of Mrs. Mary A. McClung",
  "date_str": "March 03, 1933",
  "date_iso": "1933-03-03",
  "president": "Herbert Hoover",
  "text": "Mrs. Mary A. McClung may be appointed to an appropriate position in the Department of Agriculture without regard to the Civil Service rules.\nMrs. McClung has been employed in an excepted position in a confidential capacity in the Department of Agriculture since April 1, 1929, and her services can be used to advantage.\nThis order is recommended by the Secretary of Agriculture.\nHERBERT HOOVER\nThe White House,\nMarch 3, 1933."
}