{
  "url": "https://www.presidency.ucsb.edu/documents/executive-order-7721-enlarging-willapa-harbor-migratory-bird-refuge",
  "eo_number": "7721",
  "title": "Executive Order 7721—Enlarging Willapa Harbor Migratory Bird Refuge",
  "date_str": "October 08, 1937",
  "date_iso": "1937-10-08",
  "president": "Franklin D. Roosevelt",
  "text": "WASHINGTON\nBy virtue of and pursuant to the authority vested in me as President of the United States and in order to effectuate further the purposes of the Migratory\nBird Conservation Act (45 Stat. 1222), it is ordered that the following-described lands and accretions thereto, comprising approximately 5,000 acres in Pacific County, Washington, acquired or to be acquired by the United States, be, and they are hereby, reserved and set apart, subject to existing valid rights, for the use of the Department of Agriculture as an addition to the Willapa Harbor Migratory Bird Refuge established by Executive Order No. 7541 of January 22, 1937:\nProvided\n, that any private lands within the area described shall become a part of the refuge upon the acquisition of title thereto or lease thereof by the United States:\nWILLAMETTE MERIDIAN\nT. 11 N., R. 10 W.,\nSec. 5, lots 5 and 6, and SW¼ SW¼;\nSecs. 6 and 7;\nSec. 8, lots 2 to 6, inclusive, and NW¼ NW¼;\nSec. 17, lots 3, 4, and 5;\nSecs. 18 and 19;\nSec. 20, lots 1 to 5, inclusive, SW¼ NW¼, and W½SW¼;\nSec. 29, lots 2, 3, and 4, and NW¼ NW¼;\nSec. 30, all.\nT. 11 N., R. 11 W.,\nSecs. 1, 12, and 13.\nT. 12 N., R. 11 W.,\nSecs. 25 and 36.\nFRANKLIN D ROOSEVELT\nThe White House,\nOctober 8, 1937."
}