{
  "url": "https://www.presidency.ucsb.edu/documents/executive-order-8437-power-site-restoration-no-493-partial-revocation-executive-order",
  "eo_number": "8437",
  "title": "Executive Order 8437âPower Site Restoration No. 493. Partial Revocation of Executive Order of November 22, 1924, Creating Power Site Reserve No. 759",
  "date_str": "June 11, 1940",
  "date_iso": "1940-06-11",
  "president": "Franklin D. Roosevelt",
  "text": "NEW MEXICO\nBy virtue of the authority vested in me by the act of June 25, 1910, ch. 421, 36 Stat. 847, the Executive Order of November 22, 1924, creating Power Site Reserve No. 759, is hereby revoked as to the following-described lands:\nNEW MEXICO PRINCIPAL MERIDIAN\nT. 12 S., R. 20 W.,\nsec. 1, lot 4, SWÂžNWÂž , and SWÂž;\nsec. 3, WÂ―;\nsec. 4, NEÂž;\nsec. 10, WÂ―EÂ―, and EÂ―WÂ―;\nsec. 15, WÂ―EÂ― , EÂ―WÂ―, and SEÂžSEÂž;\nsec. 22, WÂ―EÂ―, and WÂ―;\nsec. 23, EÂ―SEÂž ;\nsec. 24, SWÂž;\nsec. 26, NEÂžNEÂž, SÂ―NEÂž, NEÂžSWÂž, SÂ―SWÂž, and SEÂž;\nsec. 27, NÂ― and SWÂž;\nsec. 28, EÂ― and SWÂž;\nsec. 29, SÂ―;\nsec. 30, SÂ―SWÂž, and SEÂž;\nsec. 31, NWÂž, and SÂ―SEÂž;\nsec. 32, SÂ―SÂ―;\nsec. 33, SÂ―SÂ―;\nsec. 34, SÂ―SÂ―;\nsec. 35, NÂ―NWÂž, and SÂ―SWÂž.\nT. 13 S., R. 20 W.,\nsec. 3, NWÂž;\nsec. 4, NÂ― ;\nsec. 5, NÂ―, and NÂ―SÂ―;\nsec. 6, all.\nFRANKLIN D. ROOSEVELT\nThe White House,\nJune 11, 1940."
}