{
  "url": "https://www.presidency.ucsb.edu/documents/executive-order-the-death-millard-fillmore",
  "eo_number": "PENDING-1874-03-09-executive-order-the-death-mill",
  "title": "Executive Order [on the death of Millard Fillmore]",
  "date_str": "March 09, 1874",
  "date_iso": "1874-03-09",
  "president": "Ulysses S. Grant",
  "text": "GENERAL ORDERS, NO. 22\nWAR DEPARTMENT,\nADJUTANT-GENERAL'S OFFICE\nI. The following order has been received from the President of the United States:\nEXECUTIVE MANSION,\nWashington\n,\nMarch 9, 1874.\nIt is with deep regret that the President announces to the people of the United States the death of Millard Fillmore, one of his honored predecessors, who died at Buffalo, N.Y., last evening.\nThe long-continued and useful public service and eminent purity of character of the deceased ex-President will be remembered beyond the days of mourning in which a nation will be thrown by the event which is thus announced.\nAs a mark of respect to his memory, it is ordered that the Executive Mansion and the several Departments at Washington be draped in mourning until the close of the day on which the funeral shall take place, and that all business be suspended on the day of the funeral.\nIt is further ordered that the War and Navy Departments cause suitable military and naval honors to be paid on the occasion to the memory of the eminent citizen whose life is now closed.\nU.S. GRANT.\nBy the President:\nHAMILTON FISH,\nSecretary of State.\nII. In compliance with the President's instructions, the troops will be paraded at 10 o'clock a. m. on the day after the receipt of this order at each military post, when the order will be read to them, and the labors of that day will thereafter cease.\nThe national flag will be displayed at half-staff.\nAt dawn of day thirteen guns will be fired, and afterwards at intervals of thirty minutes between the rising and setting sun a single gun, and at the close of the day a national salute of thirty-seven guns.\nThe officers of the Army will wear crape on the left arm and on their swords and the colors of the several regiments will be put in mourning for the period of thirty days.\nBy order of the Secretary of War:\nE. D. TOWNSEND,\nAdjutant-General.\nSpecial Order\nNAVY DEPARTMENT,\nWashington,\nMarch 9, 1874.\nThe President of the United States announces the death of ex-President Millard Fillmore in the following order:\nIn pursuance of the foregoing order, it is hereby directed that the ensign at each naval station and of each vessel of the United States Navy in commission be hoisted at half-mast from sunrise to sunset, and that a gun be fired at intervals of every half hour from sunrise to sunset at each naval station and on board of flagships and of vessels acting singly, on Thursday, the 12th instant, the day of the funeral, where this order may be received in time, otherwise on the day after its receipt.\nThe officers of the Navy and Marine Corps will wear the usual badge of mourning attached to the sword hilt and on the left arm for the period of thirty days.\nGEO. M. ROBESON,\nSecretary of the Navy."
}