{
  "url": "https://www.presidency.ucsb.edu/documents/executive-order-establishment-gila-bend-reserve",
  "eo_number": "PENDING-1882-12-12-executive-order-establishment-",
  "title": "Executive Order—Establishment of Gila Bend Reserve",
  "date_str": "December 12, 1882",
  "date_iso": "1882-12-12",
  "president": "Chester A. Arthur",
  "text": "[Pima Agency; occupied by Papago tribe; area 35 square miles.]\nEXECUTIVE MANSION, December 12, 1882.\nIt is hereby ordered that the following tract of country in the Territory of Arizona, viz, township 5 south, range 5 west, Gila and Salt River meridian, excepting section 18 thereof, be, and the same is hereby, withdrawn from sale and settlement and set apart for the use and occupancy of the Papago and other Indians now settled there, and such other Indians as the Secretary of the Interior may see fit to settle thereon.\nCHESTER A. ARTHUR."
}